aichatbot/__init__.py
aichatbot/chatbot.py
aichatbot/speech2text.py
aichatbot/utils.py
aichatbot-0.0.5.dist-info/LICENSE
aichatbot-0.0.5.dist-info/METADATA
aichatbot-0.0.5.dist-info/WHEEL
aichatbot-0.0.5.dist-info/top_level.txt
aichatbot-0.0.5.dist-info/RECORD
